thegoat/__init__.py
thegoat/cli.py
thegoat/config.py
thegoat/whois.py
thegoat-0.2.dist-info/LICENSE
thegoat-0.2.dist-info/METADATA
thegoat-0.2.dist-info/WHEEL
thegoat-0.2.dist-info/entry_points.txt
thegoat-0.2.dist-info/top_level.txt
thegoat-0.2.dist-info/RECORD
